inmanta_plugins/postgresql/__init__.py
inmanta_plugins/postgresql/resources.py
inmanta_plugins/postgresql/setup.cfg
inmanta_plugins/postgresql/model/_init.cf
inmanta_plugins/postgresql/model/ha.cf
inmanta_plugins/postgresql/templates/pg_hba.conf.j2
inmanta_plugins/postgresql/templates/pg_hba_master.conf.j2
inmanta_plugins/postgresql/templates/postgresql.conf.j2
inmanta_plugins/postgresql/templates/postgresql_master.conf.j2
inmanta_plugins/postgresql/templates/recovery.conf.j2
inmanta_module_postgresql-1.0.12.dist-info/METADATA
inmanta_module_postgresql-1.0.12.dist-info/WHEEL
inmanta_module_postgresql-1.0.12.dist-info/top_level.txt
inmanta_module_postgresql-1.0.12.dist-info/RECORD
